talktracker/__init__.py
talktracker/analysis.py
talktracker/talkanalysis.py
talktracker/talktracker.py
talktracker-0.12.dist-info/METADATA
talktracker-0.12.dist-info/RECORD
talktracker-0.12.dist-info/WHEEL
talktracker-0.12.dist-info/top_level.txt
