Metadata-Version: 2.1
Name: talktracker
Version: 0.12
Summary: Records information about the performance of participants in a group discussion
Home-page: https://github.com/mohammadbashiri/talktracker
Author: Mohammad Bashiri
Author-email: mohammadbashiri93@gmail.com
License: MIT
Platform: UNKNOWN
Requires-Dist: numpy
Requires-Dist: matplotlib
Requires-Dist: click
